[{"user":"U0A6T0LNT","type":"message","subtype":"channel_join","text":"<@U0A6T0LNT|brandon> has joined the channel","ts":"1444498331.000002"},{"user":"U0A6T0LNT","purpose":"sharing playlists and recommendations","type":"message","subtype":"channel_purpose","text":"<@U0A6T0LNT|brandon> set the channel purpose: sharing playlists and recommendations","ts":"1444498332.000003"},{"user":"U0B6U4WVC","inviter":"U0A6T0LNT","type":"message","subtype":"channel_join","text":"<@U0B6U4WVC|connorgalleher> has joined the channel","ts":"1444498640.000004"},{"user":"U0A6V6PHS","inviter":"U0A6T0LNT","type":"message","subtype":"channel_join","text":"<@U0A6V6PHS|bgillespie> has joined the channel","ts":"1444498640.000005"},{"user":"U0A6Z2QE4","inviter":"U0A6T0LNT","type":"message","subtype":"channel_join","text":"<@U0A6Z2QE4|bpl> has joined the channel","ts":"1444498640.000006"},{"user":"U0B7LF484","inviter":"U0A6T0LNT","type":"message","subtype":"channel_join","text":"<@U0B7LF484|bwoolston> has joined the channel","ts":"1444498640.000007"},{"user":"U0A6T3S2F","inviter":"U0A6T0LNT","type":"message","subtype":"channel_join","text":"<@U0A6T3S2F|galenlynch> has joined the channel","ts":"1444498640.000008"},{"user":"U0A6TU7L3","inviter":"U0A6T0LNT","type":"message","subtype":"channel_join","text":"<@U0A6TU7L3|mariagillespie> has joined the channel","ts":"1444498640.000009"},{"user":"U0B061R88","inviter":"U0A6T0LNT","type":"message","subtype":"channel_join","text":"<@U0B061R88|lindsayad> has joined the channel","ts":"1444498640.000010"},{"user":"U0A9CJF51","inviter":"U0A6T0LNT","type":"message","subtype":"channel_join","text":"<@U0A9CJF51|erik.curtis> has joined the channel","ts":"1444498640.000011"},{"user":"U0A6WE73P","inviter":"U0A6T0LNT","type":"message","subtype":"channel_join","text":"<@U0A6WE73P|mbyron> has joined the channel","ts":"1444498640.000012"},{"user":"U0BTTCL9M","inviter":"U0A6T0LNT","type":"message","subtype":"channel_join","text":"<@U0BTTCL9M|melaniedrake> has joined the channel","ts":"1444498640.000013"},{"user":"U0C0XE7CZ","inviter":"U0A6T0LNT","type":"message","subtype":"channel_join","text":"<@U0C0XE7CZ|matt.s.curtis> has joined the channel","ts":"1444498640.000014"},{"user":"U0BRLU4PL","inviter":"U0A6T0LNT","type":"message","subtype":"channel_join","text":"<@U0BRLU4PL|rodgelers> has joined the channel","ts":"1444498640.000015"},{"user":"U0AVA8KDH","inviter":"U0A6T0LNT","type":"message","subtype":"channel_join","text":"<@U0AVA8KDH|sean.mac> has joined the channel","ts":"1444498641.000016"},{"user":"U0A6XP8JF","inviter":"U0A6T0LNT","type":"message","subtype":"channel_join","text":"<@U0A6XP8JF|zach> has joined the channel","ts":"1444498641.000017"},{"user":"U0BRM12RE","inviter":"U0A6T0LNT","type":"message","subtype":"channel_join","text":"<@U0BRM12RE|sbernecker> has joined the channel","ts":"1444498641.000018"},{"user":"U0B0A0NAX","inviter":"U0A6T0LNT","type":"message","subtype":"channel_join","text":"<@U0B0A0NAX|seekarete> has joined the channel","ts":"1444498641.000019"},{"type":"message","user":"U0A6T0LNT","text":"<!channel>: since Grooveshark imploded, is anyone using anything _other_ than Spotify?","ts":"1444498699.000020"},{"type":"message","user":"U0B0A0NAX","text":"Pandora. Or a real radio.","ts":"1444502282.000021"},{"type":"message","user":"U0AVA8KDH","text":"Honestly, I mostly pick and choose what suits me at the moment on Youtube (and keep a few hand-curated, suited-to-mood playlists there).","ts":"1444521172.000022"},{"type":"message","user":"U0A6T0LNT","text":"I still have Pandora, but I rarely use it","ts":"1444521250.000023"},{"type":"message","user":"U0A6WE73P","text":"Pandora+NPR+local radio","ts":"1444524907.000024"},{"type":"message","user":"U0A6WE73P","text":"also, if you are into new music of the indieish variety, check out NoiseTrade","ts":"1444524920.000025"},{"type":"message","user":"U0A6WE73P","text":"I get a ton of free music from them (well, I download it and then usually tip the artist directly through their website)","ts":"1444524940.000026"},{"type":"message","user":"U0A6WE73P","text":"I get almost daily emails from them with several EPs of new artists, each with an accompanying list of similar-sounding bands (e.g. \"Sounds Like: Mumford and Sons, The Lone Bellow, Trampled By Turtles\")","ts":"1444525070.000027"},{"type":"message","user":"U0A6Z2QE4","text":"Pandora, reverb nation, sound cloud","ts":"1444534127.000028"},{"type":"message","user":"U0A6XP8JF","text":"I know people who use Rdio and Apple Music","ts":"1444586155.000029"},{"type":"message","user":"U0A6T0LNT","text":"I make a new Spotify playlist each month to highlight the stuff that I'm listening to","ts":"1444683093.000030"},{"type":"message","user":"U0A6T0LNT","text":"some months it's not much","ts":"1444683097.000031"},{"type":"message","user":"U0A6T0LNT","text":"other months it's a lot","ts":"1444683128.000032"},{"type":"message","user":"U0A6T0LNT","text":"<http:\/\/open.spotify.com\/user\/1266586855>","ts":"1444683128.000033"},{"type":"message","user":"U0A6T0LNT","text":"I'm seeing Wolf Alice on Friday at a fun venue in the Mission called The Chapel (a converted church)","ts":"1444683180.000034"},{"type":"message","user":"U0A6T0LNT","text":"<https:\/\/play.spotify.com\/artist\/3btzEQD6sugImIHPMRgkwV>","attachments":[{"service_name":"Spotify","service_url":"https:\/\/www.spotify.com","title":"Top tracks for Wolf Alice","title_link":"https:\/\/play.spotify.com\/artist\/3btzEQD6sugImIHPMRgkwV","thumb_url":"https:\/\/d3rt1990lpmkn.cloudfront.net\/cover\/f974a52e5a160b47ad093dd2d54dd62a28e11d27","thumb_width":300,"thumb_height":300,"fallback":"Spotify Audio: Link: Top tracks for Wolf Alice","audio_html":"<iframe src=\"https:\/\/embed.spotify.com\/?uri=spotify:artist:3btzEQD6sugImIHPMRgkwV\" width=\"300\" height=\"380\" frameborder=\"0\" allowtransparency=\"true\"><\/iframe>","audio_html_width":300,"audio_html_height":380,"from_url":"https:\/\/play.spotify.com\/artist\/3btzEQD6sugImIHPMRgkwV","id":1}],"ts":"1444683192.000035"},{"type":"message","user":"U0A6T0LNT","text":"whoaaaa Slack you've outdone yourself","ts":"1444683212.000037"},{"type":"message","user":"U0A6T0LNT","text":"this month I've been a little obsessed with HEALTH's new album, DEATH MAGIC: <http:\/\/open.spotify.com\/album\/2a5KZ4rwrXIm28LvcyjYz5>","attachments":[{"service_name":"Spotify","service_url":"https:\/\/www.spotify.com","title":"Health - DEATH MAGIC","title_link":"http:\/\/open.spotify.com\/album\/2a5KZ4rwrXIm28LvcyjYz5","thumb_url":"https:\/\/d3rt1990lpmkn.cloudfront.net\/cover\/678b9256b8dfce969a9e69714785ad1a92ef17f2","thumb_width":300,"thumb_height":300,"fallback":"Spotify Audio: Link: Health - DEATH MAGIC","audio_html":"<iframe src=\"https:\/\/embed.spotify.com\/?uri=spotify:album:2a5KZ4rwrXIm28LvcyjYz5\" width=\"300\" height=\"380\" frameborder=\"0\" allowtransparency=\"true\"><\/iframe>","audio_html_width":300,"audio_html_height":380,"from_url":"http:\/\/open.spotify.com\/album\/2a5KZ4rwrXIm28LvcyjYz5","id":1}],"ts":"1444683353.000038"},{"type":"message","user":"U0A6T0LNT","text":"not my usual fare, but it's fun","ts":"1444683379.000040"},{"type":"message","user":"U0A6T0LNT","text":"Saw Wolf Alice last night at The Chapel in SF","ts":"1445021723.000041"},{"type":"message","user":"U0A6T0LNT","text":"best show I've ever attended","edited":{"user":"U0A6T0LNT","ts":"1445021748.000000"},"ts":"1445021733.000042"},{"type":"message","user":"U0A6T0LNT","text":"can't say I've never had a band pour champagne directly into my mouth from the stage at the end of a show","ts":"1445021833.000045"},{"type":"message","user":"U0A6T0LNT","text":"but that's an advantage of an awesome crowd at an awesome venue at the last stop on a tour :simple_smile:","ts":"1445021873.000046"},{"type":"message","user":"U0A6T0LNT","text":"<http:\/\/open.spotify.com\/album\/6bRsXeFIUgPfYLZNprki2h>","attachments":[{"service_name":"Spotify","service_url":"https:\/\/www.spotify.com","title":"Wolf Alice - My Love Is Cool","title_link":"http:\/\/open.spotify.com\/album\/6bRsXeFIUgPfYLZNprki2h","thumb_url":"https:\/\/d3rt1990lpmkn.cloudfront.net\/cover\/a1c4628d57b4a7176876000e6335efb4d0a13d1a","thumb_width":300,"thumb_height":300,"fallback":"Spotify Audio: Link: Wolf Alice - My Love Is Cool","audio_html":"<iframe src=\"https:\/\/embed.spotify.com\/?uri=spotify:album:6bRsXeFIUgPfYLZNprki2h\" width=\"300\" height=\"380\" frameborder=\"0\" allowtransparency=\"true\"><\/iframe>","audio_html_width":300,"audio_html_height":380,"from_url":"http:\/\/open.spotify.com\/album\/6bRsXeFIUgPfYLZNprki2h","id":1}],"ts":"1445021969.000047"},{"type":"message","user":"U0A6T0LNT","text":"<http:\/\/open.spotify.com\/user\/1231035644\/playlist\/0Uj7zRG0av6AdrfQL73tLr>","attachments":[{"service_name":"Spotify","service_url":"https:\/\/www.spotify.com","title":"Rick and Morty - OST","title_link":"http:\/\/open.spotify.com\/user\/1231035644\/playlist\/0Uj7zRG0av6AdrfQL73tLr","thumb_url":"https:\/\/d3rt1990lpmkn.cloudfront.net\/300\/069bcd4c58e5de6c154950da2c56edf25b82d2ce083ae9b590e9566bdfbc1a6a7f61f25f02bfdcf2451185499a23ad59dcc7e6f50d39d207ba0c384ea161a7198aa22300359e0f02c8014a2bc39acf7d","thumb_width":300,"thumb_height":300,"fallback":"Spotify Audio: Link: Rick and Morty - OST","audio_html":"<iframe src=\"https:\/\/embed.spotify.com\/?uri=spotify:user:1231035644:playlist:0Uj7zRG0av6AdrfQL73tLr\" width=\"300\" height=\"380\" frameborder=\"0\" allowtransparency=\"true\"><\/iframe>","audio_html_width":300,"audio_html_height":380,"from_url":"http:\/\/open.spotify.com\/user\/1231035644\/playlist\/0Uj7zRG0av6AdrfQL73tLr","id":1}],"ts":"1445324548.000052"},{"type":"message","user":"U0A6XP8JF","text":"listening to this rn","ts":"1445353887.000054","reactions":[{"name":"horse","users":["U0A6T0LNT"],"count":1}]},{"type":"message","user":"U0A6XP8JF","text":"wow \"shake that ass bitch\"","ts":"1445355332.000055"},{"type":"message","user":"U0A6XP8JF","text":"whole song is over the top","ts":"1445355343.000056"},{"type":"message","user":"U0A6T0LNT","text":"I came across _Do You Feel It?_ on Pandora and looked this up","ts":"1445356727.000057"},{"type":"message","user":"U0A6T0LNT","text":"(YES I FEEL IT)","ts":"1445356734.000058"},{"type":"message","user":"U0A6T0LNT","text":"it's impossible to hear _For the Damaged Coda_ without wondering what Evil Morty is up to","ts":"1445356867.000059"},{"type":"message","user":"U0B0A0NAX","text":"<http:\/\/redfang.bandcamp.com\/yum> WW34-HCQ3","ts":"1445359832.000060","reactions":[{"name":"horse","users":["U0A6T0LNT"],"count":1}]},{"type":"message","user":"U0A6T0LNT","text":"I get a \"Please enter your track\/album code\" when I click","ts":"1445361444.000061"},{"type":"message","user":"U0A6T0LNT","text":"oh. duh.","ts":"1445361448.000062","reactions":[{"name":"turtle","users":["U0B0A0NAX"],"count":1}]},{"type":"message","user":"U0A6WE73P","text":"thinking of upgrading to a paid music streaming service.  Differences between Spotify and Pandora?","ts":"1445455494.000063"},{"type":"message","user":"U0A6T0LNT","text":"Spotify lets you play what you want, Pandora reads your mind and makes radio stations","ts":"1445455589.000064"},{"type":"message","user":"U0A6XP8JF","text":"and it\u2019s bad at reading your mind","ts":"1445455600.000065"},{"type":"message","user":"U0A6XP8JF","text":"the big win with spotify","ts":"1445455605.000066"},{"type":"message","user":"U0A6XP8JF","text":"is that you can subscribe to other people\u2019s lists","ts":"1445455622.000067"},{"type":"message","user":"U0A6XP8JF","text":"if you\u2019re lazy like me","ts":"1445455626.000068"},{"type":"message","user":"U0A6WE73P","text":"yeah, it seems like it definitely has more functionality than Pandora-- I've been trying it out for the past couple of days and haven't gotten to explore much more than the radio functions (but those are really buggy compared to Pandora)","ts":"1445455689.000069"},{"type":"message","user":"U0A6WE73P","text":"which makes sense, given that they are different services conceived to do different things","ts":"1445455710.000070"},{"type":"message","user":"U0A6XP8JF","text":"I\u2019ve heard a lot of good things about the Spotify discover queue (which autopicks for you based on what you listen to rather than a given song or artist) recently","ts":"1445455749.000071"},{"type":"message","user":"U0A6T0LNT","text":"the Spotify Discover stuff is _awesome_","ts":"1445455817.000072"},{"type":"message","user":"U0A6WE73P","text":"ooooh, new Josh Pyke album!  <https:\/\/open.spotify.com\/album\/7cCwoDcz37vfRNYiVqIc6W>","attachments":[{"service_name":"Spotify","service_url":"https:\/\/www.spotify.com","title":"Josh Pyke - But For All These Shrinking Hearts (Deluxe Version)","title_link":"https:\/\/open.spotify.com\/album\/7cCwoDcz37vfRNYiVqIc6W","thumb_url":"https:\/\/d3rt1990lpmkn.cloudfront.net\/cover\/fc5901446b842626cd9d1042433d7d61f7d9db6b","thumb_width":300,"thumb_height":300,"fallback":"Spotify Audio: Link: Josh Pyke - But For All These Shrinking Hearts (Deluxe Version)","audio_html":"<iframe src=\"https:\/\/embed.spotify.com\/?uri=spotify:album:7cCwoDcz37vfRNYiVqIc6W\" width=\"300\" height=\"380\" frameborder=\"0\" allowtransparency=\"true\"><\/iframe>","audio_html_width":300,"audio_html_height":380,"from_url":"https:\/\/open.spotify.com\/album\/7cCwoDcz37vfRNYiVqIc6W","id":1}],"ts":"1445456381.000073"},{"type":"message","user":"U0A6WE73P","text":"highly recommend if you like mellowish acoustic indie rock","ts":"1445456414.000075"},{"type":"message","user":"U0A6T0LNT","text":"*|BC| 2015-10* <http:\/\/open.spotify.com\/user\/1266586855\/playlist\/0ZXmRPbamsObZot3pRkczX>","ts":"1445614853.000079"},{"type":"message","user":"U0A6T0LNT","text":"(any idea why snippets are no longer posting?)","ts":"1445621826.000080"},{"type":"message","user":"U0A6XP8JF","text":"are they not? :disappointed:","ts":"1445623100.000081"},{"type":"message","user":"U0A6T0LNT","text":"my snippet didn't post here or on <#C0A6T3YAW>","ts":"1445624185.000082"},{"type":"message","user":"U0C0XE7CZ","text":"Maybe you have it turned off.","ts":"1445633829.000083"},{"type":"message","user":"U0C0XE7CZ","text":"Margaret's stuff is still working since yours today.","ts":"1445633878.000084"},{"type":"message","user":"U0C0XE7CZ","text":"Test: <https:\/\/www.youtube.com\/watch?v=o0xt1QVsigc>","attachments":[{"service_name":"YouTube","service_url":"https:\/\/www.youtube.com\/","title":"cloud cult - take your medicine","title_link":"https:\/\/www.youtube.com\/watch?v=o0xt1QVsigc","author_name":"recycledlovesongs","author_link":"https:\/\/www.youtube.com\/user\/recycledlovesongs","thumb_url":"https:\/\/i.ytimg.com\/vi\/o0xt1QVsigc\/hqdefault.jpg","thumb_width":480,"thumb_height":360,"fallback":"YouTube Video: cloud cult - take your medicine","video_html":"<iframe width=\"400\" height=\"300\" src=\"https:\/\/www.youtube.com\/embed\/o0xt1QVsigc?feature=oembed\" frameborder=\"0\" allowfullscreen><\/iframe>","video_html_width":400,"video_html_height":300,"from_url":"https:\/\/www.youtube.com\/watch?v=o0xt1QVsigc","id":1}],"ts":"1445633950.000085"},{"type":"message","user":"U0C0XE7CZ","text":"Yeah, mine works too.","ts":"1445633955.000087"},{"type":"message","user":"U0C0XE7CZ","text":"<@U0A6T0LNT>: You're still using the client version, right?","ts":"1445634064.000088"},{"type":"message","user":"U0A6T0LNT","text":"<https:\/\/www.youtube.com\/watch?v=BkmZPRz8B3Q>","attachments":[{"service_name":"YouTube","service_url":"https:\/\/www.youtube.com\/","title":"Paramagnetism of Manganese Salts","title_link":"https:\/\/www.youtube.com\/watch?v=BkmZPRz8B3Q","author_name":"Brandon Curtis","author_link":"https:\/\/www.youtube.com\/user\/BCurt9000","thumb_url":"https:\/\/i.ytimg.com\/vi\/BkmZPRz8B3Q\/hqdefault.jpg","thumb_width":480,"thumb_height":360,"fallback":"YouTube Video: Paramagnetism of Manganese Salts","video_html":"<iframe width=\"400\" height=\"225\" src=\"https:\/\/www.youtube.com\/embed\/BkmZPRz8B3Q?feature=oembed\" frameborder=\"0\" allowfullscreen><\/iframe>","video_html_width":400,"video_html_height":225,"from_url":"https:\/\/www.youtube.com\/watch?v=BkmZPRz8B3Q","id":1}],"ts":"1445637779.000089"},{"type":"message","user":"U0A6T0LNT","text":"YouTube works fine, it was just Spotify that wasn't working","ts":"1445637796.000091"},{"type":"message","user":"U0A6XP8JF","text":"that could be an error in any of a number of places","ts":"1445637819.000092"},{"type":"message","user":"U0A6XP8JF","text":"slack, spotify, your client","ts":"1445637827.000093"},{"type":"message","user":"U0A6XP8JF","text":"hard to debug","ts":"1445637830.000094"},{"type":"message","user":"U0A6T0LNT","text":"<http:\/\/open.spotify.com\/user\/1266586855\/playlist\/0ZXmRPbamsObZot3pRkczX>","attachments":[{"service_name":"Spotify","service_url":"https:\/\/www.spotify.com","title":"|BC| 2015-10","title_link":"http:\/\/open.spotify.com\/user\/1266586855\/playlist\/0ZXmRPbamsObZot3pRkczX","thumb_url":"https:\/\/d3rt1990lpmkn.cloudfront.net\/300\/ba3860a72f98adf23a7808be31526be7aea5ed77940073eda09c494bcf9d6f4726f4b977b724b4defcf49b86d0cd2fd3d7bf6fcde5c122a6ac18f740387f4c38764eb969da7280f2c9f8b0acb630e4a3","thumb_width":300,"thumb_height":300,"fallback":"Spotify Audio: Link: |BC| 2015-10","audio_html":"<iframe src=\"https:\/\/embed.spotify.com\/?uri=spotify:user:1266586855:playlist:0ZXmRPbamsObZot3pRkczX\" width=\"300\" height=\"380\" frameborder=\"0\" allowtransparency=\"true\"><\/iframe>","audio_html_width":300,"audio_html_height":380,"from_url":"http:\/\/open.spotify.com\/user\/1266586855\/playlist\/0ZXmRPbamsObZot3pRkczX","id":1}],"ts":"1445637883.000095"},{"type":"message","user":"U0A6XP8JF","text":"seems like it was transient","ts":"1445637898.000097"},{"type":"message","user":"U0A6T0LNT","text":"yeah, I think Spotify was having trouble earlier","ts":"1445637900.000098"}]